./otmorris-0.18.post1.dist-info/RECORD
./otmorris-0.18.post1.dist-info/WHEEL
./otmorris-0.18.post1.dist-info/METADATA
./otmorris/_otmorris.so
./otmorris/__init__.py
./otmorris/otmorris.py
./otmorris/.dylibs/libotmorris.0.dylib
