Metadata-Version: 1.2
Name: otmorris
Version: 0.18.post1
Summary: Morris module
Home-page: http://www.openturns.org
Author: OpenTURNS Developers
Author-email: users@openturns.org
License: LGPL
Keywords: probability reliability sensitivity metamodel
Platform: any
Classifier: Development Status :: 5 - Production/Stable
Classifier: License :: OSI Approved :: GNU Lesser General Public License v3 or later (LGPLv3+)
Classifier: Programming Language :: C++
Classifier: Topic :: Scientific/Engineering :: Mathematics
Classifier: Intended Audience :: Science/Research
Requires-Dist: openturns (>=1.20)
